ao3statscraper/__init__.py
ao3statscraper/__version__.py
ao3statscraper/ao3requester.py
ao3statscraper/configuration.py
ao3statscraper/interactive_legend.py
ao3statscraper/plotting.py
ao3statscraper/pw.py
ao3statscraper/scrape.py
ao3statscraper/statsdata.py
ao3statscraper/utils.py
ao3statscraper/scripts/__init__.py
ao3statscraper/scripts/ao3_hits_to_kudos.py
ao3statscraper/scripts/ao3_purge_stats_data.py
ao3statscraper/scripts/ao3diff.py
ao3statscraper/scripts/ao3get.py
ao3statscraper/scripts/ao3plot.py
ao3statscraper-0.5.2.dist-info/licenses/LICENSE
ao3statscraper-0.5.2.dist-info/METADATA
ao3statscraper-0.5.2.dist-info/WHEEL
ao3statscraper-0.5.2.dist-info/entry_points.txt
ao3statscraper-0.5.2.dist-info/top_level.txt
ao3statscraper-0.5.2.dist-info/RECORD
