Metadata-Version: 2.4
Name: ao3statscraper
Version: 0.5.2
Summary: Scrape stats from your AO3 stats page.
Author-email: AthenasLilOwl <athenaslilowl@protonmail.com>
License-Expression: GPL-3.0-or-later
Project-URL: Homepage, https://gitlab.com/athenaslilowl1/AO3StatScraper
Keywords: AO3,web,stats,matplotlib
Classifier: Programming Language :: Python
Classifier: Programming Language :: Python :: 3
Classifier: Intended Audience :: End Users/Desktop
License-File: LICENSE
Requires-Dist: bs4
Requires-Dist: datetime
Requires-Dist: lxml
Requires-Dist: matplotlib>=3.6
Requires-Dist: packaging
Requires-Dist: pandas>=2.2.0
Requires-Dist: pycryptodome>=3.20
Requires-Dist: pyjson
Requires-Dist: pyyaml
Requires-Dist: requests
Requires-Dist: tabulate
Requires-Dist: termcolor
Dynamic: license-file
